mapel_elections-2.1.11.dist-info/WHEEL
mapel_elections-2.1.11.dist-info/LICENSE.txt
mapel_elections-2.1.11.dist-info/top_level.txt
mapel_elections-2.1.11.dist-info/RECORD
mapel_elections-2.1.11.dist-info/METADATA
mapel/elections/__init__.py
mapel/elections/distances_.py
mapel/elections/features_.py
mapel/elections/cultures_.py
mapel/elections/features/scores.py
mapel/elections/features/power_index.py
mapel/elections/features/__init__.py
mapel/elections/features/partylist.py
mapel/elections/features/vc_diversity.py
mapel/elections/features/dap_approximate.py
mapel/elections/features/dependent_rounding.py
mapel/elections/features/dimensionality.py
mapel/elections/features/entropy.py
mapel/elections/features/other.py
mapel/elections/features/proportionality_degree.py
mapel/elections/features/cohesive.py
mapel/elections/features/diversity.py
mapel/elections/features/ranging_cc.py
mapel/elections/features/banzhaf_cc.py
mapel/elections/features/approx.py
mapel/elections/features/clustering.py
mapel/elections/features/distortion.py
mapel/elections/features/justified_representation.py
mapel/elections/cultures/identity.py
mapel/elections/cultures/__init__.py
mapel/elections/cultures/group_separable.py
mapel/elections/cultures/params.py
mapel/elections/cultures/guardians_plus.py
mapel/elections/cultures/euclidean.py
mapel/elections/cultures/converters.py
mapel/elections/cultures/mallows.py
mapel/elections/cultures/fake.py
mapel/elections/cultures/urn.py
mapel/elections/cultures/unused.py
mapel/elections/cultures/preflib.py
mapel/elections/cultures/guardians.py
mapel/elections/cultures/nonstandard/alliances.py
mapel/elections/cultures/nonstandard/field_experiment.py
mapel/elections/cultures/nonstandard/parties.py
mapel/elections/cultures/sampling/samplemat.py
mapel/elections/cultures/to_be_removed/mallows_urn.py
mapel/elections/cultures/to_be_removed/euclidean.py
mapel/elections/cultures/matrices/single_crossing_matrices.py
mapel/elections/cultures/matrices/group_separable_matrices.py
mapel/elections/cultures/matrices/single_peaked_matrices.py
mapel/elections/objects/OrdinalElectionExperiment.py
mapel/elections/objects/__init__.py
