Metadata-Version: 2.1
Name: mapel-elections
Version: 2.1.11
Summary: Map of Elections
Author-email: Stanislaw Szufa <s.szufa@gmail.com>, Niclas Boehmer <niclas.boehmer@tu-berlin.de>, Piotr Faliszewski <faliszew@agh.edu.pl>, Lukasz Janeczko <lukij1997@gmail.com>, Andrzej Kaczmarczyk <andrzej.kaczmarczyk@agh.edu.pl>, Tomasz Was <tomasz.t.was@gmail.com>
License: Copyright (c) 2018-2022 Stanislaw Szufa and contributors
Classifier: Programming Language :: Python :: 3
Classifier: License :: OSI Approved :: MIT License
Classifier: Operating System :: OS Independent
Requires-Python: >=3.7
License-File: LICENSE.txt
Requires-Dist: mapel-core>=2.0.0
Provides-Extra: extras
Requires-Dist: cplex>=20.1.0.1; extra == "extras"
Requires-Dist: abcvoting~=2.0.0b0; extra == "extras"
Requires-Dist: pulp~=2.5.1; extra == "extras"
Requires-Dist: permanent; extra == "extras"
